<?xml version="1.0" encoding="utf-8"?><regions><name>Vinnytsia Oblast</name><name>Volyn Oblast</name><name>Luhansk Oblast</name><name>Dnipropetrovsk Oblast</name><name>Donetsk Oblast</name><name>Zhytomyr Oblast</name><name>Zakarpattia Oblast</name><name>Zaporizhia Oblast</name><name>Ivano-Frankivsk Oblast</name><name>Kiev</name><name>Kiev Oblast</name><name>Kirovohrad Oblast</name><name>Sevastopol</name><name>Autonomous Republic of Crimea</name><name>Lviv Oblast</name><name>Mykolaiv Oblast</name><name>Odessa Oblast</name><name>Poltava Oblast</name><name>Rivne Oblast</name><name>Sumy Oblast</name><name>Ternopil Oblast</name><name>Kharkiv Oblast</name><name>Kherson Oblast</name><name>Khmelnytskyi Oblast</name><name>Cherkasy Oblast</name><name>Chernihiv Oblast</name><name>Chernivtsi Oblast</name></regions>